docpipe/__init__.py
docpipe/citations.py
docpipe/html.py
docpipe/matchers.py
docpipe/pdf.py
docpipe/pipeline.py
docpipe/soffice.py
docpipe/xmlutils.py
docpipe/tests/__init__.py
docpipe/tests/test_html.py
docpipe/tests/test_matchers.py
docpipe/tests/test_xmlutils.py
docpipe-0.0.2.post1.dist-info/LICENSE-LESSER.txt
docpipe-0.0.2.post1.dist-info/LICENSE.txt
docpipe-0.0.2.post1.dist-info/METADATA
docpipe-0.0.2.post1.dist-info/WHEEL
docpipe-0.0.2.post1.dist-info/top_level.txt
docpipe-0.0.2.post1.dist-info/RECORD
