Metadata-Version: 2.1
Name: docpipe
Version: 0.0.2.post1
Summary: A simple pipeline for processing documents
Author-email: Greg Kempe <greg@laws.africa>
Project-URL: Homepage, https://github.com/laws-africa/docpipe
Project-URL: Bug Tracker, https://github.com/laws-africa/docpipe/issues
Classifier: Programming Language :: Python :: 3
Classifier: License :: OSI Approved :: MIT License
Classifier: Operating System :: OS Independent
Requires-Python: >=3.7
License-File: LICENSE-LESSER.txt
License-File: LICENSE.txt
Requires-Dist: cobalt (>=6)
Requires-Dist: cssutils (>=2)
Requires-Dist: lxml (>=4.0)
Provides-Extra: test
Requires-Dist: nose ; extra == 'test'
